watchout/__init__.py
watchout/config.py
watchout/main.py
watchout/runner.py
watchout/status.py
watchout-0.0.1.dist-info/METADATA
watchout-0.0.1.dist-info/WHEEL
watchout-0.0.1.dist-info/entry_points.txt
watchout-0.0.1.dist-info/licenses/LICENSE
watchout-0.0.1.dist-info/RECORD
