Metadata-Version: 2.4
Name: watchout
Version: 0.0.1
Summary: Run your python scripts and compare the outputs
Author-email: Ryan Young <dev@ryayoung.com>
License-Expression: MIT
License-File: LICENSE
Classifier: Development Status :: 3 - Alpha
Classifier: Intended Audience :: Developers
Classifier: License :: OSI Approved :: MIT License
Classifier: Operating System :: OS Independent
Classifier: Programming Language :: Python :: 3.12
Classifier: Topic :: Software Development :: Libraries
Requires-Dist: click
Requires-Dist: humanize
Requires-Dist: prompt-toolkit
Requires-Dist: watchfiles
